{
"meta":{"test_sets":[],"test_metrics":[],"learn_metrics":[{"best_value":"Min","name":"RMSE"}],"launch_mode":"Train","parameters":"","iteration_count":100,"learn_sets":["learn"],"name":"experiment"},
"iterations":[
{"learn":[17622628.3],"iteration":0,"passed_time":0.1142084734,"remaining_time":11.30663886},
{"learn":[16258336.19],"iteration":1,"passed_time":0.1239360939,"remaining_time":6.072868599},
{"learn":[15395371.59],"iteration":2,"passed_time":0.1329570437,"remaining_time":4.298944414},
{"learn":[14846254.1],"iteration":3,"passed_time":0.1418482861,"remaining_time":3.404358866},
{"learn":[14547337.8],"iteration":4,"passed_time":0.1519440925,"remaining_time":2.886937757},
{"learn":[14291112.38],"iteration":5,"passed_time":0.1621715362,"remaining_time":2.540687401},
{"learn":[14096392.47],"iteration":6,"passed_time":0.1697651546,"remaining_time":2.25545134},
{"learn":[13874720.58],"iteration":7,"passed_time":0.1767289965,"remaining_time":2.03238346},
{"learn":[13649296.81],"iteration":8,"passed_time":0.1842118096,"remaining_time":1.862586075},
{"learn":[13564151.62],"iteration":9,"passed_time":0.1906012562,"remaining_time":1.715411306},
{"learn":[13488488.86],"iteration":10,"passed_time":0.1964742674,"remaining_time":1.589655436},
{"learn":[13350563],"iteration":11,"passed_time":0.2006204406,"remaining_time":1.471216564},
{"learn":[13284631.17],"iteration":12,"passed_time":0.2049575245,"remaining_time":1.371638818},
{"learn":[13144053.76],"iteration":13,"passed_time":0.2096639689,"remaining_time":1.287935809},
{"learn":[13073976.15],"iteration":14,"passed_time":0.213861807,"remaining_time":1.211883573},
{"learn":[12884703.07],"iteration":15,"passed_time":0.2175243892,"remaining_time":1.142003043},
{"learn":[12850872.96],"iteration":16,"passed_time":0.2215425218,"remaining_time":1.081648783},
{"learn":[12761906.89],"iteration":17,"passed_time":0.2246841745,"remaining_time":1.023561239},
{"learn":[12680670.38],"iteration":18,"passed_time":0.2278823604,"remaining_time":0.9714984838},
{"learn":[12573780.71],"iteration":19,"passed_time":0.2314150771,"remaining_time":0.9256603085},
{"learn":[12542953.76],"iteration":20,"passed_time":0.2345718392,"remaining_time":0.882436919},
{"learn":[12454367.71],"iteration":21,"passed_time":0.2382116438,"remaining_time":0.8445685553},
{"learn":[12415970.86],"iteration":22,"passed_time":0.2412742276,"remaining_time":0.8077441533},
{"learn":[12393581.67],"iteration":23,"passed_time":0.2440988937,"remaining_time":0.7729798299},
{"learn":[12374663.36],"iteration":24,"passed_time":0.2473549064,"remaining_time":0.7420647191},
{"learn":[12320889.4],"iteration":25,"passed_time":0.2505558737,"remaining_time":0.7131205635},
{"learn":[12175107.74],"iteration":26,"passed_time":0.2542095038,"remaining_time":0.6873071769},
{"learn":[12086446.4],"iteration":27,"passed_time":0.2576445896,"remaining_time":0.662514659},
{"learn":[12067825.49],"iteration":28,"passed_time":0.2610108927,"remaining_time":0.6390266683},
{"learn":[12019119.16],"iteration":29,"passed_time":0.2647574416,"remaining_time":0.6177673638},
{"learn":[11929226.71],"iteration":30,"passed_time":0.2679741644,"remaining_time":0.5964586239},
{"learn":[11900869.97],"iteration":31,"passed_time":0.2718764134,"remaining_time":0.5777373785},
{"learn":[11872852.79],"iteration":32,"passed_time":0.2748712527,"remaining_time":0.5580719373},
{"learn":[11828678.51],"iteration":33,"passed_time":0.2781789419,"remaining_time":0.5399944167},
{"learn":[11812365.27],"iteration":34,"passed_time":0.2811313949,"remaining_time":0.5221011619},
{"learn":[11799367.95],"iteration":35,"passed_time":0.2844121872,"remaining_time":0.5056216661},
{"learn":[11786122.57],"iteration":36,"passed_time":0.288456663,"remaining_time":0.4911559397},
{"learn":[11752951.05],"iteration":37,"passed_time":0.2917832826,"remaining_time":0.476067461},
{"learn":[11744313.66],"iteration":38,"passed_time":0.2946523513,"remaining_time":0.4608664983},
{"learn":[11687675.77],"iteration":39,"passed_time":0.2975181298,"remaining_time":0.4462771948},
{"learn":[11627914.04],"iteration":40,"passed_time":0.301612154,"remaining_time":0.434027246},
{"learn":[11580646.96],"iteration":41,"passed_time":0.3052054941,"remaining_time":0.4214742538},
{"learn":[11552408.9],"iteration":42,"passed_time":0.3085434308,"remaining_time":0.4089994315},
{"learn":[11407166.34],"iteration":43,"passed_time":0.3117310201,"remaining_time":0.396748571},
{"learn":[11381805.51],"iteration":44,"passed_time":0.3153147691,"remaining_time":0.3853847177},
{"learn":[11369392.16],"iteration":45,"passed_time":0.3190845472,"remaining_time":0.374577512},
{"learn":[11340883.9],"iteration":46,"passed_time":0.322300959,"remaining_time":0.3634457623},
{"learn":[11320630.3],"iteration":47,"passed_time":0.3255185465,"remaining_time":0.352645092},
{"learn":[11311248.29],"iteration":48,"passed_time":0.3297073664,"remaining_time":0.34316481},
{"learn":[11291771.83],"iteration":49,"passed_time":0.3341360829,"remaining_time":0.3341360829},
{"learn":[11282848.77],"iteration":50,"passed_time":0.3379420058,"remaining_time":0.3246893781},
{"learn":[11259247.23],"iteration":51,"passed_time":0.3421544441,"remaining_time":0.3158348715},
{"learn":[11137786.85],"iteration":52,"passed_time":0.3464563603,"remaining_time":0.3072348855},
{"learn":[11039625.75],"iteration":53,"passed_time":0.3506598369,"remaining_time":0.2987102314},
{"learn":[10977419.1],"iteration":54,"passed_time":0.3548210759,"remaining_time":0.290308153},
{"learn":[10908524.92],"iteration":55,"passed_time":0.3584568023,"remaining_time":0.2816446304},
{"learn":[10852195.23],"iteration":56,"passed_time":0.3623105369,"remaining_time":0.273321984},
{"learn":[10835338.73],"iteration":57,"passed_time":0.3663630355,"remaining_time":0.2652973705},
{"learn":[10788989.99],"iteration":58,"passed_time":0.3702166033,"remaining_time":0.257269165},
{"learn":[10768897.13],"iteration":59,"passed_time":0.3737929149,"remaining_time":0.2491952766},
{"learn":[10738166.79],"iteration":60,"passed_time":0.3777734234,"remaining_time":0.2415272707},
{"learn":[10700532.09],"iteration":61,"passed_time":0.3815591509,"remaining_time":0.2338588344},
{"learn":[10689757.82],"iteration":62,"passed_time":0.3852183013,"remaining_time":0.2262393198},
{"learn":[10671435.47],"iteration":63,"passed_time":0.3892887092,"remaining_time":0.2189748989},
{"learn":[10651070.89],"iteration":64,"passed_time":0.3932339749,"remaining_time":0.2117413711},
{"learn":[10604378.94],"iteration":65,"passed_time":0.3968059696,"remaining_time":0.2044151965},
{"learn":[10591984.14],"iteration":66,"passed_time":0.4008079669,"remaining_time":0.1974128792},
{"learn":[10560496.3],"iteration":67,"passed_time":0.404330358,"remaining_time":0.1902731096},
{"learn":[10544878.91],"iteration":68,"passed_time":0.408519555,"remaining_time":0.1835377711},
{"learn":[10531101.43],"iteration":69,"passed_time":0.4116420438,"remaining_time":0.1764180188},
{"learn":[10505033.61],"iteration":70,"passed_time":0.4154282774,"remaining_time":0.1696819725},
{"learn":[10492926.83],"iteration":71,"passed_time":0.4191319884,"remaining_time":0.1629957733},
{"learn":[10483512.71],"iteration":72,"passed_time":0.4229891191,"remaining_time":0.1564480303},
{"learn":[10462717.61],"iteration":73,"passed_time":0.4264809233,"remaining_time":0.1498446487},
{"learn":[10454800.7],"iteration":74,"passed_time":0.4298681266,"remaining_time":0.1432893755},
{"learn":[10380906.21],"iteration":75,"passed_time":0.4337446985,"remaining_time":0.13697201},
{"learn":[10367313.34],"iteration":76,"passed_time":0.4375346388,"remaining_time":0.1306921648},
{"learn":[10345289.17],"iteration":77,"passed_time":0.440734577,"remaining_time":0.1243097525},
{"learn":[10328114.67],"iteration":78,"passed_time":0.4443388523,"remaining_time":0.1181153911},
{"learn":[10321637.5],"iteration":79,"passed_time":0.448399235,"remaining_time":0.1120998088},
{"learn":[10307937.69],"iteration":80,"passed_time":0.452344889,"remaining_time":0.1061055913},
{"learn":[10294454.44],"iteration":81,"passed_time":0.4565336333,"remaining_time":0.1002147},
{"learn":[10281278.57],"iteration":82,"passed_time":0.4604171344,"remaining_time":0.09430230463},
{"learn":[10228210.18],"iteration":83,"passed_time":0.4648337231,"remaining_time":0.08853975678},
{"learn":[10188195.44],"iteration":84,"passed_time":0.469309671,"remaining_time":0.08281935371},
{"learn":[10177217.73],"iteration":85,"passed_time":0.4731500264,"remaining_time":0.0770244229},
{"learn":[10143964.29],"iteration":86,"passed_time":0.4766765657,"remaining_time":0.0712275328},
{"learn":[10134237.65],"iteration":87,"passed_time":0.4806882059,"remaining_time":0.06554839171},
{"learn":[10121655.5],"iteration":88,"passed_time":0.4846121698,"remaining_time":0.05989588616},
{"learn":[10115296.3],"iteration":89,"passed_time":0.4885347289,"remaining_time":0.05428163654},
{"learn":[10110163.08],"iteration":90,"passed_time":0.4919344498,"remaining_time":0.04865285767},
{"learn":[10098490.04],"iteration":91,"passed_time":0.4959545792,"remaining_time":0.04312648515},
{"learn":[10062597.53],"iteration":92,"passed_time":0.4999763896,"remaining_time":0.03763263148},
{"learn":[10051348.41],"iteration":93,"passed_time":0.503516956,"remaining_time":0.03213938017},
{"learn":[10033503.4],"iteration":94,"passed_time":0.5069588577,"remaining_time":0.02668204514},
{"learn":[10021911.1],"iteration":95,"passed_time":0.5106734602,"remaining_time":0.02127806084},
{"learn":[10003634.37],"iteration":96,"passed_time":0.5147457667,"remaining_time":0.01591997217},
{"learn":[9988820.598],"iteration":97,"passed_time":0.5183827526,"remaining_time":0.01057923985},
{"learn":[9978931.976],"iteration":98,"passed_time":0.521927593,"remaining_time":0.005271995889},
{"learn":[9964341.684],"iteration":99,"passed_time":0.5253849287,"remaining_time":0}
]}